{
  "description": "",
  "key": "8c73775e-42e1-4562-ab39-5cbbb9612b43",
  "tags": [
    {
      "key": "ae7524f0-6f1c-4777-8272-650b53f704b6",
      "name": "name",
      "value": "eulomelo",
      "labelerLogin": "",
      "createdAt": "2025-03-14 14:55:49.312674+00:00",
      "updatedAt": "2025-04-09 21:03:41.644454+00:00"
    },
    {
      "key": "f83d1177-8e7f-4b72-87b5-111c4716059b",
      "name": "labels",
      "value": [
        {
          "label_id": 0,
          "name": "Person",
          "color": "#c06060",
          "type": "cuboid"
        }
      ],
      "labelerLogin": "",
      "createdAt": "2025-03-14 14:55:49.312674+00:00",
      "updatedAt": "2025-04-09 21:03:41.644454+00:00"
    }
  ],
  "objects": [
    {
      "key": "943cece0-1826-4f55-93aa-953cf3fccb37",
      "classTitle": "Person",
      "tags": [
        {
          "key": "d38b8046-7542-48a2-a4b3-41fbcc483063",
          "name": "occluded",
          "value": "false",
          "labelerLogin": "",
          "createdAt": "2025-03-14 14:55:49.312674+00:00",
          "updatedAt": "2025-04-09 21:03:41.644454+00:00"
        },
        {
          "key": "4ed16357-dbb9-4795-9f4f-f0c4dc90eaec",
          "name": "keyframe",
          "value": "false",
          "labelerLogin": "",
          "createdAt": "2025-03-14 14:55:49.312674+00:00",
          "updatedAt": "2025-04-09 21:03:41.644454+00:00"
        }
      ],
      "objects": [],
      "figures": [],
      "labelerLogin": "",
      "createdAt": "2025-03-14 14:55:49.312674+00:00",
      "updatedAt": "2025-04-09 21:03:41.644454+00:00"
    },
    {
      "key": "c0db069e-d736-4234-816f-d2f9451a61b8",
      "classTitle": "Person",
      "tags": [
        {
          "key": "73c58abb-1699-4bd4-b1bd-aae8aa775621",
          "name": "occluded",
          "value": "false",
          "labelerLogin": "",
          "createdAt": "2025-03-14 14:55:49.312674+00:00",
          "updatedAt": "2025-04-09 21:03:41.644454+00:00"
        },
        {
          "key": "df0e0a0b-9980-4d12-8b23-2977eefda8f8",
          "name": "keyframe",
          "value": "false",
          "labelerLogin": "",
          "createdAt": "2025-03-14 14:55:49.312674+00:00",
          "updatedAt": "2025-04-09 21:03:41.644454+00:00"
        }
      ],
      "objects": [],
      "figures": [],
      "labelerLogin": "",
      "createdAt": "2025-03-14 14:55:49.312674+00:00",
      "updatedAt": "2025-04-09 21:03:41.644454+00:00"
    },
    {
      "key": "c42561bf-a03a-4935-85ba-5d96cddee8d5",
      "classTitle": "Person",
      "tags": [
        {
          "key": "cbe8fba9-2b31-4294-9279-7b693c57a74e",
          "name": "occluded",
          "value": "false",
          "labelerLogin": "",
          "createdAt": "2025-03-14 14:55:49.312674+00:00",
          "updatedAt": "2025-04-09 21:03:41.644454+00:00"
        },
        {
          "key": "2ca03566-4a1f-4c28-b607-21f38a4eef5c",
          "name": "keyframe",
          "value": "false",
          "labelerLogin": "",
          "createdAt": "2025-03-14 14:55:49.312674+00:00",
          "updatedAt": "2025-04-09 21:03:41.644454+00:00"
        }
      ],
      "objects": [],
      "figures": [],
      "labelerLogin": "",
      "createdAt": "2025-03-14 14:55:49.312674+00:00",
      "updatedAt": "2025-04-09 21:03:41.644454+00:00"
    },
    {
      "key": "c59024c3-8eee-43ce-87ab-f3de14d3b36b",
      "classTitle": "Person",
      "tags": [
        {
          "key": "5fadc927-5a70-4e15-ad3b-8b43bca1e0fe",
          "name": "occluded",
          "value": "false",
          "labelerLogin": "",
          "createdAt": "2025-03-14 14:55:49.312674+00:00",
          "updatedAt": "2025-04-09 21:03:41.644454+00:00"
        },
        {
          "key": "5b8499a5-7556-47bd-9e69-e220e4d3491d",
          "name": "keyframe",
          "value": "false",
          "labelerLogin": "",
          "createdAt": "2025-03-14 14:55:49.312674+00:00",
          "updatedAt": "2025-04-09 21:03:41.644454+00:00"
        }
      ],
      "objects": [],
      "figures": [],
      "labelerLogin": "",
      "createdAt": "2025-03-14 14:55:49.312674+00:00",
      "updatedAt": "2025-04-09 21:03:41.644454+00:00"
    },
    {
      "key": "f8f55302-3005-42f3-b581-567cf7f1200d",
      "classTitle": "Person",
      "tags": [
        {
          "key": "8f6cf032-bb26-4d76-a098-d4945244058a",
          "name": "occluded",
          "value": "false",
          "labelerLogin": "",
          "createdAt": "2025-03-14 14:55:49.312674+00:00",
          "updatedAt": "2025-04-09 21:03:41.644454+00:00"
        },
        {
          "key": "589199c6-2435-4d1e-9956-d1a0d9b5c736",
          "name": "keyframe",
          "value": "false",
          "labelerLogin": "",
          "createdAt": "2025-03-14 14:55:49.312674+00:00",
          "updatedAt": "2025-04-09 21:03:41.644454+00:00"
        }
      ],
      "objects": [],
      "figures": [],
      "labelerLogin": "",
      "createdAt": "2025-03-14 14:55:49.312674+00:00",
      "updatedAt": "2025-04-09 21:03:41.644454+00:00"
    }
  ],
  "figures": [
    {
      "key": "f746e290-5046-4836-9311-2c99aff3cfc7",
      "objectKey": "943cece0-1826-4f55-93aa-953cf3fccb37",
      "geometryType": "cuboid_3d",
      "geometry": {
        "position": {
          "x": 8.1,
          "y": -1.5,
          "z": -1.28
        },
        "rotation": {
          "x": 0.0,
          "y": 0.0,
          "z": 0.0
        },
        "dimensions": {
          "x": 0.59,
          "y": 0.59,
          "z": 1.54
        }
      },
      "labelerLogin": "",
      "createdAt": "2025-03-14 14:55:49.312674+00:00",
      "updatedAt": "2025-04-09 21:03:41.644454+00:00"
    },
    {
      "key": "9bddf1e0-74aa-4430-bcb6-cfe81facce0a",
      "objectKey": "c0db069e-d736-4234-816f-d2f9451a61b8",
      "geometryType": "cuboid_3d",
      "geometry": {
        "position": {
          "x": 6.17,
          "y": -1.48,
          "z": -1.31
        },
        "rotation": {
          "x": 0.0,
          "y": 0.0,
          "z": 0.0
        },
        "dimensions": {
          "x": 0.59,
          "y": 0.59,
          "z": 1.65
        }
      },
      "labelerLogin": "",
      "createdAt": "2025-03-14 14:55:49.312674+00:00",
      "updatedAt": "2025-04-09 21:03:41.644454+00:00"
    },
    {
      "key": "5a92fb7a-d1b2-4a15-9d13-3f05632efc4f",
      "objectKey": "c42561bf-a03a-4935-85ba-5d96cddee8d5",
      "geometryType": "cuboid_3d",
      "geometry": {
        "position": {
          "x": 4.3,
          "y": -0.79,
          "z": -1.33
        },
        "rotation": {
          "x": 0.0,
          "y": 0.0,
          "z": 0.0
        },
        "dimensions": {
          "x": 0.59,
          "y": 0.59,
          "z": 1.65
        }
      },
      "labelerLogin": "",
      "createdAt": "2025-03-14 14:55:49.312674+00:00",
      "updatedAt": "2025-04-09 21:03:41.644454+00:00"
    },
    {
      "key": "116d4ef2-58f0-4141-a725-04d5970a0f7e",
      "objectKey": "c59024c3-8eee-43ce-87ab-f3de14d3b36b",
      "geometryType": "cuboid_3d",
      "geometry": {
        "position": {
          "x": 4.01,
          "y": -2.4,
          "z": -1.33
        },
        "rotation": {
          "x": 0.0,
          "y": 0.0,
          "z": 0.0
        },
        "dimensions": {
          "x": 0.59,
          "y": 0.59,
          "z": 1.73
        }
      },
      "labelerLogin": "",
      "createdAt": "2025-03-14 14:55:49.312674+00:00",
      "updatedAt": "2025-04-09 21:03:41.644454+00:00"
    },
    {
      "key": "e90add94-8dd7-4826-9dcd-8b303f349108",
      "objectKey": "f8f55302-3005-42f3-b581-567cf7f1200d",
      "geometryType": "cuboid_3d",
      "geometry": {
        "position": {
          "x": 6.74,
          "y": -3.36,
          "z": -1.32
        },
        "rotation": {
          "x": 0.0,
          "y": 0.0,
          "z": 0.0
        },
        "dimensions": {
          "x": 0.59,
          "y": 0.59,
          "z": 1.73
        }
      },
      "labelerLogin": "",
      "createdAt": "2025-03-14 14:55:49.312674+00:00",
      "updatedAt": "2025-04-09 21:03:41.644454+00:00"
    }
  ]
}