{
  "description": "",
  "key": "a2632fa8-2f2b-4b80-9f22-5bbe84bdada0",
  "tags": [
    {
      "key": "e44ee8b1-09ac-4f58-ba6d-180a356ed229",
      "name": "name",
      "value": "eulomelo",
      "labelerLogin": "",
      "createdAt": "2025-03-14 14:55:49.312674+00:00",
      "updatedAt": "2025-04-09 21:03:41.644454+00:00"
    },
    {
      "key": "6f5b083f-805b-4a21-a77f-94f36e743a00",
      "name": "labels",
      "value": [
        {
          "label_id": 0,
          "name": "Person",
          "color": "#c06060",
          "type": "cuboid"
        }
      ],
      "labelerLogin": "",
      "createdAt": "2025-03-14 14:55:49.312674+00:00",
      "updatedAt": "2025-04-09 21:03:41.644454+00:00"
    }
  ],
  "objects": [
    {
      "key": "943cece0-1826-4f55-93aa-953cf3fccb37",
      "classTitle": "Person",
      "tags": [
        {
          "key": "5994fdaa-5127-4cd3-afe5-4f915b33d782",
          "name": "occluded",
          "value": "false",
          "labelerLogin": "",
          "createdAt": "2025-03-14 14:55:49.312674+00:00",
          "updatedAt": "2025-04-09 21:03:41.644454+00:00"
        },
        {
          "key": "02ebd3b9-d26f-495a-b12f-5d0d0866eaae",
          "name": "keyframe",
          "value": "false",
          "labelerLogin": "",
          "createdAt": "2025-03-14 14:55:49.312674+00:00",
          "updatedAt": "2025-04-09 21:03:41.644454+00:00"
        }
      ],
      "objects": [],
      "figures": [],
      "labelerLogin": "",
      "createdAt": "2025-03-14 14:55:49.312674+00:00",
      "updatedAt": "2025-04-09 21:03:41.644454+00:00"
    },
    {
      "key": "c0db069e-d736-4234-816f-d2f9451a61b8",
      "classTitle": "Person",
      "tags": [
        {
          "key": "27d50aa7-2794-4710-9f9c-3cec6ac5ae6f",
          "name": "occluded",
          "value": "false",
          "labelerLogin": "",
          "createdAt": "2025-03-14 14:55:49.312674+00:00",
          "updatedAt": "2025-04-09 21:03:41.644454+00:00"
        },
        {
          "key": "ff46b664-e821-4e96-a318-b0d9a8cb072c",
          "name": "keyframe",
          "value": "false",
          "labelerLogin": "",
          "createdAt": "2025-03-14 14:55:49.312674+00:00",
          "updatedAt": "2025-04-09 21:03:41.644454+00:00"
        }
      ],
      "objects": [],
      "figures": [],
      "labelerLogin": "",
      "createdAt": "2025-03-14 14:55:49.312674+00:00",
      "updatedAt": "2025-04-09 21:03:41.644454+00:00"
    },
    {
      "key": "c42561bf-a03a-4935-85ba-5d96cddee8d5",
      "classTitle": "Person",
      "tags": [
        {
          "key": "86dea51c-427f-4f8d-86a1-6d54b041d6a1",
          "name": "occluded",
          "value": "false",
          "labelerLogin": "",
          "createdAt": "2025-03-14 14:55:49.312674+00:00",
          "updatedAt": "2025-04-09 21:03:41.644454+00:00"
        },
        {
          "key": "378b58dc-9650-46c7-9ff9-307a790e6b46",
          "name": "keyframe",
          "value": "false",
          "labelerLogin": "",
          "createdAt": "2025-03-14 14:55:49.312674+00:00",
          "updatedAt": "2025-04-09 21:03:41.644454+00:00"
        }
      ],
      "objects": [],
      "figures": [],
      "labelerLogin": "",
      "createdAt": "2025-03-14 14:55:49.312674+00:00",
      "updatedAt": "2025-04-09 21:03:41.644454+00:00"
    },
    {
      "key": "c59024c3-8eee-43ce-87ab-f3de14d3b36b",
      "classTitle": "Person",
      "tags": [
        {
          "key": "2fc342d7-e926-418f-a0e4-4a88734c7421",
          "name": "occluded",
          "value": "false",
          "labelerLogin": "",
          "createdAt": "2025-03-14 14:55:49.312674+00:00",
          "updatedAt": "2025-04-09 21:03:41.644454+00:00"
        },
        {
          "key": "5000ca6b-28c1-4293-a921-9ad1e6026a06",
          "name": "keyframe",
          "value": "false",
          "labelerLogin": "",
          "createdAt": "2025-03-14 14:55:49.312674+00:00",
          "updatedAt": "2025-04-09 21:03:41.644454+00:00"
        }
      ],
      "objects": [],
      "figures": [],
      "labelerLogin": "",
      "createdAt": "2025-03-14 14:55:49.312674+00:00",
      "updatedAt": "2025-04-09 21:03:41.644454+00:00"
    },
    {
      "key": "f8f55302-3005-42f3-b581-567cf7f1200d",
      "classTitle": "Person",
      "tags": [
        {
          "key": "5e46890f-3729-4060-8c4d-e4474c92514d",
          "name": "occluded",
          "value": "false",
          "labelerLogin": "",
          "createdAt": "2025-03-14 14:55:49.312674+00:00",
          "updatedAt": "2025-04-09 21:03:41.644454+00:00"
        },
        {
          "key": "34b45dea-c0d0-4e19-91ed-fb19fc0c50ac",
          "name": "keyframe",
          "value": "false",
          "labelerLogin": "",
          "createdAt": "2025-03-14 14:55:49.312674+00:00",
          "updatedAt": "2025-04-09 21:03:41.644454+00:00"
        }
      ],
      "objects": [],
      "figures": [],
      "labelerLogin": "",
      "createdAt": "2025-03-14 14:55:49.312674+00:00",
      "updatedAt": "2025-04-09 21:03:41.644454+00:00"
    }
  ],
  "figures": [
    {
      "key": "fef3193e-1b9c-4e3e-a140-a20e54b6e94e",
      "objectKey": "943cece0-1826-4f55-93aa-953cf3fccb37",
      "geometryType": "cuboid_3d",
      "geometry": {
        "position": {
          "x": 7.17,
          "y": -1.08,
          "z": -1.28
        },
        "rotation": {
          "x": 0.0,
          "y": 0.0,
          "z": 0.0
        },
        "dimensions": {
          "x": 0.59,
          "y": 0.59,
          "z": 1.54
        }
      },
      "labelerLogin": "",
      "createdAt": "2025-03-14 14:55:49.312674+00:00",
      "updatedAt": "2025-04-09 21:03:41.644454+00:00"
    },
    {
      "key": "5b6cee39-c662-4398-951b-44e4a64936b3",
      "objectKey": "c0db069e-d736-4234-816f-d2f9451a61b8",
      "geometryType": "cuboid_3d",
      "geometry": {
        "position": {
          "x": 5.31,
          "y": -3.8,
          "z": -1.31
        },
        "rotation": {
          "x": 0.0,
          "y": 0.0,
          "z": 0.0
        },
        "dimensions": {
          "x": 0.59,
          "y": 0.59,
          "z": 1.65
        }
      },
      "labelerLogin": "",
      "createdAt": "2025-03-14 14:55:49.312674+00:00",
      "updatedAt": "2025-04-09 21:03:41.644454+00:00"
    },
    {
      "key": "fe389bf6-45f7-4fc0-8fcc-beb77b7539bc",
      "objectKey": "c42561bf-a03a-4935-85ba-5d96cddee8d5",
      "geometryType": "cuboid_3d",
      "geometry": {
        "position": {
          "x": 4.97,
          "y": -1.56,
          "z": -1.33
        },
        "rotation": {
          "x": 0.0,
          "y": 0.0,
          "z": 0.0
        },
        "dimensions": {
          "x": 0.59,
          "y": 0.59,
          "z": 1.65
        }
      },
      "labelerLogin": "",
      "createdAt": "2025-03-14 14:55:49.312674+00:00",
      "updatedAt": "2025-04-09 21:03:41.644454+00:00"
    },
    {
      "key": "2ebdbeb0-9751-49b9-b8b1-cb2f2f5ef427",
      "objectKey": "c59024c3-8eee-43ce-87ab-f3de14d3b36b",
      "geometryType": "cuboid_3d",
      "geometry": {
        "position": {
          "x": 5.03,
          "y": -2.32,
          "z": -1.33
        },
        "rotation": {
          "x": 0.0,
          "y": 0.0,
          "z": 0.0
        },
        "dimensions": {
          "x": 0.59,
          "y": 0.59,
          "z": 1.73
        }
      },
      "labelerLogin": "",
      "createdAt": "2025-03-14 14:55:49.312674+00:00",
      "updatedAt": "2025-04-09 21:03:41.644454+00:00"
    },
    {
      "key": "4eb9b396-5e6d-42cd-a01d-3c9699b07a12",
      "objectKey": "f8f55302-3005-42f3-b581-567cf7f1200d",
      "geometryType": "cuboid_3d",
      "geometry": {
        "position": {
          "x": 5.85,
          "y": -1.26,
          "z": -1.32
        },
        "rotation": {
          "x": 0.0,
          "y": 0.0,
          "z": 0.0
        },
        "dimensions": {
          "x": 0.59,
          "y": 0.59,
          "z": 1.73
        }
      },
      "labelerLogin": "",
      "createdAt": "2025-03-14 14:55:49.312674+00:00",
      "updatedAt": "2025-04-09 21:03:41.644454+00:00"
    }
  ]
}