{
  "description": "",
  "key": "048bcc79-64b4-4ed8-84c4-0f3800aca44f",
  "tags": [
    {
      "key": "20389530-6671-4320-ae41-f460baf33efc",
      "name": "name",
      "value": "eulomelo",
      "labelerLogin": "",
      "createdAt": "2025-04-23 13:25:50.279783+00:00",
      "updatedAt": "2025-05-19 12:30:50.128674+00:00"
    },
    {
      "key": "2829d7b0-454a-4c32-a017-2c13b7678ee1",
      "name": "labels",
      "value": [
        {
          "label_id": 0,
          "name": "Person",
          "color": "#c06060",
          "type": "cuboid"
        }
      ],
      "labelerLogin": "",
      "createdAt": "2025-04-23 13:25:50.279783+00:00",
      "updatedAt": "2025-05-19 12:30:50.128674+00:00"
    }
  ],
  "objects": [
    {
      "key": "f08ecee1-1d28-45e4-b6c3-cc344e4353a9",
      "classTitle": "Person",
      "tags": [
        {
          "key": "18e7bfbd-35d6-4033-9d94-717267222936",
          "name": "occluded",
          "value": "false",
          "labelerLogin": "",
          "createdAt": "2025-04-23 13:25:50.279783+00:00",
          "updatedAt": "2025-05-19 12:30:50.128674+00:00"
        },
        {
          "key": "5cffdf14-ed70-4675-8792-3d7c1dfa1ea3",
          "name": "keyframe",
          "value": "false",
          "labelerLogin": "",
          "createdAt": "2025-04-23 13:25:50.279783+00:00",
          "updatedAt": "2025-05-19 12:30:50.128674+00:00"
        }
      ],
      "objects": [],
      "figures": [],
      "labelerLogin": "",
      "createdAt": "2025-04-23 13:25:50.279783+00:00",
      "updatedAt": "2025-05-19 12:30:50.128674+00:00"
    },
    {
      "key": "aacb71dd-d0f2-4ee0-8c8e-44b574dbca47",
      "classTitle": "Person",
      "tags": [
        {
          "key": "962ceca6-fa70-4953-8c2f-4e30fe584bfe",
          "name": "occluded",
          "value": "false",
          "labelerLogin": "",
          "createdAt": "2025-04-23 13:25:50.279783+00:00",
          "updatedAt": "2025-05-19 12:30:50.128674+00:00"
        },
        {
          "key": "179a69ed-ba89-4419-a3bc-abe0464932d7",
          "name": "keyframe",
          "value": "false",
          "labelerLogin": "",
          "createdAt": "2025-04-23 13:25:50.279783+00:00",
          "updatedAt": "2025-05-19 12:30:50.128674+00:00"
        }
      ],
      "objects": [],
      "figures": [],
      "labelerLogin": "",
      "createdAt": "2025-04-23 13:25:50.279783+00:00",
      "updatedAt": "2025-05-19 12:30:50.128674+00:00"
    },
    {
      "key": "496b378d-62be-465e-be36-8fa32e348e0b",
      "classTitle": "Person",
      "tags": [
        {
          "key": "31e39536-73c5-4dc8-9c47-240e22f674a9",
          "name": "occluded",
          "value": "false",
          "labelerLogin": "",
          "createdAt": "2025-04-23 13:25:50.279783+00:00",
          "updatedAt": "2025-05-19 12:30:50.128674+00:00"
        },
        {
          "key": "6bae090c-4612-45fe-a784-88f84b17109c",
          "name": "keyframe",
          "value": "false",
          "labelerLogin": "",
          "createdAt": "2025-04-23 13:25:50.279783+00:00",
          "updatedAt": "2025-05-19 12:30:50.128674+00:00"
        }
      ],
      "objects": [],
      "figures": [],
      "labelerLogin": "",
      "createdAt": "2025-04-23 13:25:50.279783+00:00",
      "updatedAt": "2025-05-19 12:30:50.128674+00:00"
    },
    {
      "key": "ff14653e-827f-469c-af62-e43d2dae0ef2",
      "classTitle": "Person",
      "tags": [
        {
          "key": "ac100dde-b4ff-423a-bd69-8bf61445d4bc",
          "name": "occluded",
          "value": "false",
          "labelerLogin": "",
          "createdAt": "2025-04-23 13:25:50.279783+00:00",
          "updatedAt": "2025-05-19 12:30:50.128674+00:00"
        },
        {
          "key": "e4d6c14a-54aa-4199-ad43-6b4aa8d5532e",
          "name": "keyframe",
          "value": "false",
          "labelerLogin": "",
          "createdAt": "2025-04-23 13:25:50.279783+00:00",
          "updatedAt": "2025-05-19 12:30:50.128674+00:00"
        }
      ],
      "objects": [],
      "figures": [],
      "labelerLogin": "",
      "createdAt": "2025-04-23 13:25:50.279783+00:00",
      "updatedAt": "2025-05-19 12:30:50.128674+00:00"
    },
    {
      "key": "d437da64-82e8-4300-974a-284f986ee5c8",
      "classTitle": "Person",
      "tags": [
        {
          "key": "a1062563-fc68-4a83-b60c-9ce47586600a",
          "name": "occluded",
          "value": "false",
          "labelerLogin": "",
          "createdAt": "2025-04-23 13:25:50.279783+00:00",
          "updatedAt": "2025-05-19 12:30:50.128674+00:00"
        },
        {
          "key": "fd7c8e5b-b150-4e49-a44e-842469d745d7",
          "name": "keyframe",
          "value": "false",
          "labelerLogin": "",
          "createdAt": "2025-04-23 13:25:50.279783+00:00",
          "updatedAt": "2025-05-19 12:30:50.128674+00:00"
        }
      ],
      "objects": [],
      "figures": [],
      "labelerLogin": "",
      "createdAt": "2025-04-23 13:25:50.279783+00:00",
      "updatedAt": "2025-05-19 12:30:50.128674+00:00"
    }
  ],
  "figures": [
    {
      "key": "e750144b-7a33-4c20-9578-81cc4e2ff9c1",
      "objectKey": "f08ecee1-1d28-45e4-b6c3-cc344e4353a9",
      "geometryType": "cuboid_3d",
      "geometry": {
        "position": {
          "x": 4.9,
          "y": -1.68,
          "z": -1.18
        },
        "rotation": {
          "x": 0.0,
          "y": 0.0,
          "z": 0.0
        },
        "dimensions": {
          "x": 0.55,
          "y": 0.55,
          "z": 1.86
        }
      },
      "labelerLogin": "",
      "createdAt": "2025-04-23 13:25:50.279783+00:00",
      "updatedAt": "2025-05-19 12:30:50.128674+00:00"
    },
    {
      "key": "f94340f9-ad66-4976-a4d2-47aa42bb73bc",
      "objectKey": "aacb71dd-d0f2-4ee0-8c8e-44b574dbca47",
      "geometryType": "cuboid_3d",
      "geometry": {
        "position": {
          "x": 6.83,
          "y": -1.39,
          "z": -1.21
        },
        "rotation": {
          "x": 0.0,
          "y": 0.0,
          "z": 0.0
        },
        "dimensions": {
          "x": 0.54,
          "y": 0.55,
          "z": 1.86
        }
      },
      "labelerLogin": "",
      "createdAt": "2025-04-23 13:25:50.279783+00:00",
      "updatedAt": "2025-05-19 12:30:50.128674+00:00"
    },
    {
      "key": "8c2e3d3e-8936-4f27-8f46-238e47f5b2ee",
      "objectKey": "496b378d-62be-465e-be36-8fa32e348e0b",
      "geometryType": "cuboid_3d",
      "geometry": {
        "position": {
          "x": 5.79,
          "y": -2.37,
          "z": -1.2
        },
        "rotation": {
          "x": 0.0,
          "y": 0.0,
          "z": 0.0
        },
        "dimensions": {
          "x": 0.57,
          "y": 0.55,
          "z": 1.86
        }
      },
      "labelerLogin": "",
      "createdAt": "2025-04-23 13:25:50.279783+00:00",
      "updatedAt": "2025-05-19 12:30:50.128674+00:00"
    },
    {
      "key": "b6bfda10-963f-497d-a0d1-84ab3ca89857",
      "objectKey": "ff14653e-827f-469c-af62-e43d2dae0ef2",
      "geometryType": "cuboid_3d",
      "geometry": {
        "position": {
          "x": 6.27,
          "y": -4.38,
          "z": -1.17
        },
        "rotation": {
          "x": 0.0,
          "y": 0.0,
          "z": 0.0
        },
        "dimensions": {
          "x": 0.58,
          "y": 0.58,
          "z": 1.86
        }
      },
      "labelerLogin": "",
      "createdAt": "2025-04-23 13:25:50.279783+00:00",
      "updatedAt": "2025-05-19 12:30:50.128674+00:00"
    },
    {
      "key": "195d53db-2313-4b80-be0d-0399ec7a3218",
      "objectKey": "d437da64-82e8-4300-974a-284f986ee5c8",
      "geometryType": "cuboid_3d",
      "geometry": {
        "position": {
          "x": 5.69,
          "y": -1.34,
          "z": -1.25
        },
        "rotation": {
          "x": 0.0,
          "y": 0.0,
          "z": 0.0
        },
        "dimensions": {
          "x": 0.58,
          "y": 0.57,
          "z": 1.86
        }
      },
      "labelerLogin": "",
      "createdAt": "2025-04-23 13:25:50.279783+00:00",
      "updatedAt": "2025-05-19 12:30:50.128674+00:00"
    }
  ]
}