{
  "description": "",
  "key": "5690ad0c-5575-4518-8e6b-130e139980eb",
  "tags": [
    {
      "key": "50a2cf46-1401-4bee-8bf8-298e72d1481e",
      "name": "name",
      "value": "django",
      "labelerLogin": "",
      "createdAt": "2025-02-17 15:43:32.082847+00:00",
      "updatedAt": "2025-02-17 20:39:51.912570+00:00"
    },
    {
      "key": "90691ab5-c579-41c3-a6a1-006eda00540c",
      "name": "labels",
      "value": [
        {
          "label_id": 0,
          "name": "Person",
          "color": "#c06060",
          "type": "any"
        }
      ],
      "labelerLogin": "",
      "createdAt": "2025-02-17 15:43:32.082847+00:00",
      "updatedAt": "2025-02-17 20:39:51.912570+00:00"
    }
  ],
  "objects": [
    {
      "key": "d2b7dd44-aa0e-4fa7-96e3-11925c6119f3",
      "classTitle": "Person",
      "tags": [
        {
          "key": "881e3595-f166-4d0c-8730-ec3e7d44b02c",
          "name": "occluded",
          "value": "false",
          "labelerLogin": "",
          "createdAt": "2025-02-17 15:43:32.082847+00:00",
          "updatedAt": "2025-02-17 20:39:51.912570+00:00"
        },
        {
          "key": "532d088a-f7f0-467f-97dd-6bc0e4c089d3",
          "name": "keyframe",
          "value": "false",
          "labelerLogin": "",
          "createdAt": "2025-02-17 15:43:32.082847+00:00",
          "updatedAt": "2025-02-17 20:39:51.912570+00:00"
        }
      ],
      "objects": [],
      "figures": [],
      "labelerLogin": "",
      "createdAt": "2025-02-17 15:43:32.082847+00:00",
      "updatedAt": "2025-02-17 20:39:51.912570+00:00"
    },
    {
      "key": "af68b504-ab0d-4d87-abb7-d5358f62abe0",
      "classTitle": "Person",
      "tags": [
        {
          "key": "a57c5507-da29-4aff-a52a-7265249a2b00",
          "name": "occluded",
          "value": "false",
          "labelerLogin": "",
          "createdAt": "2025-02-17 15:43:32.082847+00:00",
          "updatedAt": "2025-02-17 20:39:51.912570+00:00"
        },
        {
          "key": "c61cea58-fec1-41ff-b810-b4b910a23fd4",
          "name": "keyframe",
          "value": "false",
          "labelerLogin": "",
          "createdAt": "2025-02-17 15:43:32.082847+00:00",
          "updatedAt": "2025-02-17 20:39:51.912570+00:00"
        }
      ],
      "objects": [],
      "figures": [],
      "labelerLogin": "",
      "createdAt": "2025-02-17 15:43:32.082847+00:00",
      "updatedAt": "2025-02-17 20:39:51.912570+00:00"
    },
    {
      "key": "15fcc25a-039a-41d6-ae14-b2d8a3e4b835",
      "classTitle": "Person",
      "tags": [
        {
          "key": "80971c89-b512-489c-bc71-cbcea7703ee3",
          "name": "occluded",
          "value": "false",
          "labelerLogin": "",
          "createdAt": "2025-02-17 15:43:32.082847+00:00",
          "updatedAt": "2025-02-17 20:39:51.912570+00:00"
        },
        {
          "key": "226c1afb-5275-4355-9cb1-20ba658d90a0",
          "name": "keyframe",
          "value": "false",
          "labelerLogin": "",
          "createdAt": "2025-02-17 15:43:32.082847+00:00",
          "updatedAt": "2025-02-17 20:39:51.912570+00:00"
        }
      ],
      "objects": [],
      "figures": [],
      "labelerLogin": "",
      "createdAt": "2025-02-17 15:43:32.082847+00:00",
      "updatedAt": "2025-02-17 20:39:51.912570+00:00"
    },
    {
      "key": "8ca55062-1bfe-442a-96e4-33ba28952ffa",
      "classTitle": "Person",
      "tags": [
        {
          "key": "0ba6cb9e-3f1a-41c9-89d6-fcde2271eca1",
          "name": "occluded",
          "value": "false",
          "labelerLogin": "",
          "createdAt": "2025-02-17 15:43:32.082847+00:00",
          "updatedAt": "2025-02-17 20:39:51.912570+00:00"
        },
        {
          "key": "2c3157d0-f32f-403d-89c2-268fcda7a9d1",
          "name": "keyframe",
          "value": "false",
          "labelerLogin": "",
          "createdAt": "2025-02-17 15:43:32.082847+00:00",
          "updatedAt": "2025-02-17 20:39:51.912570+00:00"
        }
      ],
      "objects": [],
      "figures": [],
      "labelerLogin": "",
      "createdAt": "2025-02-17 15:43:32.082847+00:00",
      "updatedAt": "2025-02-17 20:39:51.912570+00:00"
    },
    {
      "key": "2baa5de9-e75c-4353-9035-2851e6ff71b4",
      "classTitle": "Person",
      "tags": [
        {
          "key": "63a39ed1-fad9-4e8f-ba61-eebed63c6776",
          "name": "occluded",
          "value": "false",
          "labelerLogin": "",
          "createdAt": "2025-02-17 15:43:32.082847+00:00",
          "updatedAt": "2025-02-17 20:39:51.912570+00:00"
        },
        {
          "key": "d731a615-3ca2-4a14-9379-4a2ec5828e1a",
          "name": "keyframe",
          "value": "false",
          "labelerLogin": "",
          "createdAt": "2025-02-17 15:43:32.082847+00:00",
          "updatedAt": "2025-02-17 20:39:51.912570+00:00"
        }
      ],
      "objects": [],
      "figures": [],
      "labelerLogin": "",
      "createdAt": "2025-02-17 15:43:32.082847+00:00",
      "updatedAt": "2025-02-17 20:39:51.912570+00:00"
    }
  ],
  "figures": [
    {
      "key": "a2d16c31-c4ff-4daa-8a93-535c0d60781a",
      "objectKey": "d2b7dd44-aa0e-4fa7-96e3-11925c6119f3",
      "geometryType": "cuboid_3d",
      "geometry": {
        "position": {
          "x": 11.18,
          "y": -1.18,
          "z": -1.21
        },
        "rotation": {
          "x": 0.0,
          "y": 0.0,
          "z": 0.0
        },
        "dimensions": {
          "x": 0.53,
          "y": 0.63,
          "z": 1.55
        }
      },
      "labelerLogin": "",
      "createdAt": "2025-02-17 15:43:32.082847+00:00",
      "updatedAt": "2025-02-17 20:39:51.912570+00:00"
    },
    {
      "key": "398ed6d2-b013-4556-b68e-7618b8d9c7ee",
      "objectKey": "af68b504-ab0d-4d87-abb7-d5358f62abe0",
      "geometryType": "cuboid_3d",
      "geometry": {
        "position": {
          "x": 10.96,
          "y": 1.0,
          "z": -1.23
        },
        "rotation": {
          "x": 0.0,
          "y": 0.0,
          "z": 0.0
        },
        "dimensions": {
          "x": 0.65,
          "y": 0.75,
          "z": 1.55
        }
      },
      "labelerLogin": "",
      "createdAt": "2025-02-17 15:43:32.082847+00:00",
      "updatedAt": "2025-02-17 20:39:51.912570+00:00"
    },
    {
      "key": "ab8f4e31-b7f4-4af2-a45d-9d2f3cebedb0",
      "objectKey": "15fcc25a-039a-41d6-ae14-b2d8a3e4b835",
      "geometryType": "cuboid_3d",
      "geometry": {
        "position": {
          "x": 2.16,
          "y": -0.44,
          "z": -1.24
        },
        "rotation": {
          "x": 0.0,
          "y": 0.0,
          "z": 0.0
        },
        "dimensions": {
          "x": 0.65,
          "y": 0.75,
          "z": 1.55
        }
      },
      "labelerLogin": "",
      "createdAt": "2025-02-17 15:43:32.082847+00:00",
      "updatedAt": "2025-02-17 20:39:51.912570+00:00"
    },
    {
      "key": "547cc6ac-6f26-4b81-a330-36587e27f747",
      "objectKey": "8ca55062-1bfe-442a-96e4-33ba28952ffa",
      "geometryType": "cuboid_3d",
      "geometry": {
        "position": {
          "x": 2.3,
          "y": 0.4,
          "z": -1.32
        },
        "rotation": {
          "x": 0.0,
          "y": 0.0,
          "z": 0.0
        },
        "dimensions": {
          "x": 0.65,
          "y": 0.75,
          "z": 1.55
        }
      },
      "labelerLogin": "",
      "createdAt": "2025-02-17 15:43:32.082847+00:00",
      "updatedAt": "2025-02-17 20:39:51.912570+00:00"
    },
    {
      "key": "a6e7cdf6-2db3-41e3-a448-b5730b12c593",
      "objectKey": "2baa5de9-e75c-4353-9035-2851e6ff71b4",
      "geometryType": "cuboid_3d",
      "geometry": {
        "position": {
          "x": 2.06,
          "y": -1.87,
          "z": -1.32
        },
        "rotation": {
          "x": 0.0,
          "y": 0.0,
          "z": 0.0
        },
        "dimensions": {
          "x": 0.65,
          "y": 0.75,
          "z": 1.55
        }
      },
      "labelerLogin": "",
      "createdAt": "2025-02-17 15:43:32.082847+00:00",
      "updatedAt": "2025-02-17 20:39:51.912570+00:00"
    }
  ]
}