{
  "description": "",
  "key": "56d1a279-4a5e-4918-8863-c29c9a8301b2",
  "tags": [
    {
      "key": "41cfe990-a051-4554-aba7-365f9eedc8df",
      "name": "name",
      "value": "eulomelo",
      "labelerLogin": "",
      "createdAt": "2025-04-23 13:08:15.977435+00:00",
      "updatedAt": "2025-04-25 15:49:25.335042+00:00"
    },
    {
      "key": "2ef63d5a-1447-4edb-a80d-1f86fa34b047",
      "name": "labels",
      "value": [
        {
          "label_id": 0,
          "name": "Person",
          "color": "#c06060",
          "type": "cuboid"
        }
      ],
      "labelerLogin": "",
      "createdAt": "2025-04-23 13:08:15.977435+00:00",
      "updatedAt": "2025-04-25 15:49:25.335042+00:00"
    }
  ],
  "objects": [
    {
      "key": "f9e99a92-3547-45f0-8ba1-4642fa443377",
      "classTitle": "Person",
      "tags": [
        {
          "key": "543b7305-5606-4788-bdae-309e8ec443db",
          "name": "occluded",
          "value": "false",
          "labelerLogin": "",
          "createdAt": "2025-04-23 13:08:15.977435+00:00",
          "updatedAt": "2025-04-25 15:49:25.335042+00:00"
        },
        {
          "key": "4f5f3ad6-b1b1-4370-bb90-6f0f9b410329",
          "name": "keyframe",
          "value": "false",
          "labelerLogin": "",
          "createdAt": "2025-04-23 13:08:15.977435+00:00",
          "updatedAt": "2025-04-25 15:49:25.335042+00:00"
        }
      ],
      "objects": [],
      "figures": [],
      "labelerLogin": "",
      "createdAt": "2025-04-23 13:08:15.977435+00:00",
      "updatedAt": "2025-04-25 15:49:25.335042+00:00"
    },
    {
      "key": "86d7aa77-436d-42f3-aea1-6c2ab3c59b4a",
      "classTitle": "Person",
      "tags": [
        {
          "key": "9f83ba73-787d-440e-a996-5f1a703e98ab",
          "name": "occluded",
          "value": "false",
          "labelerLogin": "",
          "createdAt": "2025-04-23 13:08:15.977435+00:00",
          "updatedAt": "2025-04-25 15:49:25.335042+00:00"
        },
        {
          "key": "58b5aa8c-a136-4f48-bd9a-ccf232afaef3",
          "name": "keyframe",
          "value": "false",
          "labelerLogin": "",
          "createdAt": "2025-04-23 13:08:15.977435+00:00",
          "updatedAt": "2025-04-25 15:49:25.335042+00:00"
        }
      ],
      "objects": [],
      "figures": [],
      "labelerLogin": "",
      "createdAt": "2025-04-23 13:08:15.977435+00:00",
      "updatedAt": "2025-04-25 15:49:25.335042+00:00"
    },
    {
      "key": "47653c13-72e5-4a15-ae15-0cf9cbdbb39d",
      "classTitle": "Person",
      "tags": [
        {
          "key": "b2f67965-ff51-4965-b6a6-cdf34d8fb9fc",
          "name": "occluded",
          "value": "false",
          "labelerLogin": "",
          "createdAt": "2025-04-23 13:08:15.977435+00:00",
          "updatedAt": "2025-04-25 15:49:25.335042+00:00"
        },
        {
          "key": "8fbcb202-b4a6-42e4-ac43-6a23db978442",
          "name": "keyframe",
          "value": "false",
          "labelerLogin": "",
          "createdAt": "2025-04-23 13:08:15.977435+00:00",
          "updatedAt": "2025-04-25 15:49:25.335042+00:00"
        }
      ],
      "objects": [],
      "figures": [],
      "labelerLogin": "",
      "createdAt": "2025-04-23 13:08:15.977435+00:00",
      "updatedAt": "2025-04-25 15:49:25.335042+00:00"
    },
    {
      "key": "15d6aa17-a337-4007-bf17-4f0c4144fdf0",
      "classTitle": "Person",
      "tags": [
        {
          "key": "d5a13de8-7ddc-40fa-b525-0c453166ed98",
          "name": "occluded",
          "value": "false",
          "labelerLogin": "",
          "createdAt": "2025-04-23 13:08:15.977435+00:00",
          "updatedAt": "2025-04-25 15:49:25.335042+00:00"
        },
        {
          "key": "c4a00fb4-ec98-473b-8564-d3d66b88ac4e",
          "name": "keyframe",
          "value": "false",
          "labelerLogin": "",
          "createdAt": "2025-04-23 13:08:15.977435+00:00",
          "updatedAt": "2025-04-25 15:49:25.335042+00:00"
        }
      ],
      "objects": [],
      "figures": [],
      "labelerLogin": "",
      "createdAt": "2025-04-23 13:08:15.977435+00:00",
      "updatedAt": "2025-04-25 15:49:25.335042+00:00"
    },
    {
      "key": "5858f1cf-56e3-4f0f-b2f1-047bd5fd94da",
      "classTitle": "Person",
      "tags": [
        {
          "key": "d2599eb8-df5c-4128-955b-61be7daba814",
          "name": "occluded",
          "value": "false",
          "labelerLogin": "",
          "createdAt": "2025-04-23 13:08:15.977435+00:00",
          "updatedAt": "2025-04-25 15:49:25.335042+00:00"
        },
        {
          "key": "5c28e6c3-7f3b-4c99-bd9e-8566d967de67",
          "name": "keyframe",
          "value": "false",
          "labelerLogin": "",
          "createdAt": "2025-04-23 13:08:15.977435+00:00",
          "updatedAt": "2025-04-25 15:49:25.335042+00:00"
        }
      ],
      "objects": [],
      "figures": [],
      "labelerLogin": "",
      "createdAt": "2025-04-23 13:08:15.977435+00:00",
      "updatedAt": "2025-04-25 15:49:25.335042+00:00"
    }
  ],
  "figures": [
    {
      "key": "1eba0f76-0220-4946-8099-31d036ae5448",
      "objectKey": "f9e99a92-3547-45f0-8ba1-4642fa443377",
      "geometryType": "cuboid_3d",
      "geometry": {
        "position": {
          "x": 11.05,
          "y": -2.78,
          "z": -1.27
        },
        "rotation": {
          "x": 0.0,
          "y": 0.0,
          "z": 0.0
        },
        "dimensions": {
          "x": 0.46,
          "y": 0.46,
          "z": 1.71
        }
      },
      "labelerLogin": "",
      "createdAt": "2025-04-23 13:08:15.977435+00:00",
      "updatedAt": "2025-04-25 15:49:25.335042+00:00"
    },
    {
      "key": "df221b68-6728-4852-a2df-dea621550616",
      "objectKey": "86d7aa77-436d-42f3-aea1-6c2ab3c59b4a",
      "geometryType": "cuboid_3d",
      "geometry": {
        "position": {
          "x": 11.14,
          "y": -0.77,
          "z": -1.26
        },
        "rotation": {
          "x": 0.0,
          "y": 0.0,
          "z": 0.0
        },
        "dimensions": {
          "x": 0.46,
          "y": 0.46,
          "z": 1.71
        }
      },
      "labelerLogin": "",
      "createdAt": "2025-04-23 13:08:15.977435+00:00",
      "updatedAt": "2025-04-25 15:49:25.335042+00:00"
    },
    {
      "key": "3c8c23af-5a9e-4ba9-9eca-9242ae5aa28e",
      "objectKey": "47653c13-72e5-4a15-ae15-0cf9cbdbb39d",
      "geometryType": "cuboid_3d",
      "geometry": {
        "position": {
          "x": 5.97,
          "y": -4.77,
          "z": -1.26
        },
        "rotation": {
          "x": 0.0,
          "y": 0.0,
          "z": 0.0
        },
        "dimensions": {
          "x": 0.46,
          "y": 0.46,
          "z": 1.71
        }
      },
      "labelerLogin": "",
      "createdAt": "2025-04-23 13:08:15.977435+00:00",
      "updatedAt": "2025-04-25 15:49:25.335042+00:00"
    },
    {
      "key": "93b286ea-4f5c-44a2-85ba-babd07a03e8f",
      "objectKey": "15d6aa17-a337-4007-bf17-4f0c4144fdf0",
      "geometryType": "cuboid_3d",
      "geometry": {
        "position": {
          "x": 4.7,
          "y": -7.31,
          "z": -1.21
        },
        "rotation": {
          "x": 0.0,
          "y": 0.0,
          "z": 0.0
        },
        "dimensions": {
          "x": 0.46,
          "y": 0.46,
          "z": 1.71
        }
      },
      "labelerLogin": "",
      "createdAt": "2025-04-23 13:08:15.977435+00:00",
      "updatedAt": "2025-04-25 15:49:25.335042+00:00"
    },
    {
      "key": "76b85d96-b35d-48b0-965f-ed7dfe739687",
      "objectKey": "5858f1cf-56e3-4f0f-b2f1-047bd5fd94da",
      "geometryType": "cuboid_3d",
      "geometry": {
        "position": {
          "x": 5.46,
          "y": -7.45,
          "z": -1.26
        },
        "rotation": {
          "x": 0.0,
          "y": 0.0,
          "z": 0.0
        },
        "dimensions": {
          "x": 0.46,
          "y": 0.46,
          "z": 1.71
        }
      },
      "labelerLogin": "",
      "createdAt": "2025-04-23 13:08:15.977435+00:00",
      "updatedAt": "2025-04-25 15:49:25.335042+00:00"
    }
  ]
}